unbounded_data/__init__.py
unbounded_data/datasets/__init__.py
unbounded_data/datasets/client.py
unbounded_data/high_level_api.py
unbounded_data-0.44.3.dist-info/METADATA
unbounded_data-0.44.3.dist-info/WHEEL
unbounded_data-0.44.3.dist-info/RECORD
